custom_python_logger/__init__.py
custom_python_logger/consts.py
custom_python_logger/logger.py
custom_python_logger-2.0.11.dist-info/licenses/LICENSE
custom_python_logger-2.0.11.dist-info/METADATA
custom_python_logger-2.0.11.dist-info/WHEEL
custom_python_logger-2.0.11.dist-info/top_level.txt
custom_python_logger-2.0.11.dist-info/RECORD
