Metadata-Version: 2.4
Name: custom-python-logger
Version: 2.0.11
Summary: A custom logger with color support and additional features.
Author: Avi Zaguri
License: MIT
Project-URL: Homepage, https://github.com/aviz92/custom-python-logger
Project-URL: Repository, https://github.com/aviz92/custom-python-logger
Project-URL: Issues, https://github.com/aviz92/custom-python-logger/issues
Keywords: logging,logger,color,debug,development
Classifier: Development Status :: 4 - Beta
Classifier: Intended Audience :: Developers
Classifier: Programming Language :: Python :: 3.11
Classifier: Operating System :: OS Independent
Classifier: Topic :: System :: Logging
Requires-Python: >=3.11
License-File: LICENSE
Requires-Dist: colorlog>=6.10.1
Requires-Dist: pathlib>=1.0.1
Requires-Dist: pre-commit>=4.5.0
Requires-Dist: pytest>=9.0.1
Requires-Dist: python-dotenv>=1.2.1
Requires-Dist: pyyaml>=6.0.3
Requires-Dist: setuptools>=80.9.0
Requires-Dist: wheel>=0.45.1
Dynamic: license-file
